{
    "coffees": [
      {
        "id": 1,
        "name": "Espresso",
        "image":"assets/images/espresso.jpg",
        "price": 2.50
      },
      {
        "id": 2,
        "name": "Latte",
        "image": "assets/images/latte.jpg",
        "price": 3.50
      },
      {
        "id": 3,
        "name": "Cappuccino",
        "image": "assets/images/cappuccino.jpeg",
        "price": 3.00
      },
      {
        "id": 4,
        "name": "Americano",
        "image": "assets/images/americano.jpeg",
        "price": 2.00
      },
      {
        "id": 5,
        "name": "Mocha",
        "image": "assets/images/mocha.png",
        "price": 4.00
      },
      {
        "id": 6,
        "name": "Flat White",
        "image": "assets/images/flat-white.jpg",
        "price": 3.75
      },
      {
        "id": 7,
        "name": "affogato",
        "image": "assets/images/affogato.jpeg",
        "price": 3.50
      }
    ]
  }
  